build/lib/doc/conceptual.py
build/lib/exp/stockpile/stockpile.py
build/lib/restart/main.py
build/lib/restart/restart.py
build/lib/restart/src/base.py
build/lib/restart/src/data.py
build/lib/restart/src/demand.py
build/lib/restart/src/demand_dict.py
build/lib/restart/src/demand_jhu.py
build/lib/restart/src/demand_mitre.py
build/lib/restart/src/demand_who.py
build/lib/restart/src/dtest.py
build/lib/restart/src/epi.py
build/lib/restart/src/epi_dict.py
build/lib/restart/src/epi_table.py
build/lib/restart/src/filtermodel.py
build/lib/restart/src/financial.py
build/lib/restart/src/financial_dict.py
build/lib/restart/src/financial_table.py
build/lib/restart/src/inventory.py
build/lib/restart/src/inventory_dict.py
build/lib/restart/src/load.py
build/lib/restart/src/load_csv.py
build/lib/restart/src/log.py
build/lib/restart/src/mobility.py
build/lib/restart/src/mobility_dict.py
build/lib/restart/src/mobility_table.py
build/lib/restart/src/model.py
build/lib/restart/src/organization.py
build/lib/restart/src/organization_dict.py
build/lib/restart/src/output.py
build/lib/restart/src/population.py
build/lib/restart/src/population_dict.py
build/lib/restart/src/population_oes.py
build/lib/restart/src/population_wa.py
build/lib/restart/src/resource_dict.py
build/lib/restart/src/resourcemodel.py
build/lib/restart/src/util.py
build/lib/restart/src/validate.py
doc/conceptual.py
exp/stockpile/stockpile.py
restart/main.py
restart/restart.py
restart/src/base.py
restart/src/data.py
restart/src/demand.py
restart/src/demand_dict.py
restart/src/demand_jhu.py
restart/src/demand_mitre.py
restart/src/demand_who.py
restart/src/dtest.py
restart/src/epi.py
restart/src/epi_dict.py
restart/src/epi_table.py
restart/src/filtermodel.py
restart/src/financial.py
restart/src/financial_dict.py
restart/src/financial_table.py
restart/src/inventory.py
restart/src/inventory_dict.py
restart/src/load.py
restart/src/load_csv.py
restart/src/log.py
restart/src/mobility.py
restart/src/mobility_dict.py
restartus-2.5.0.1.dist-info/METADATA
restartus-2.5.0.1.dist-info/WHEEL
restartus-2.5.0.1.dist-info/top_level.txt
restartus-2.5.0.1.dist-info/RECORD
