Metadata-Version: 2.1
Name: restartus
Version: 2.5.0.1
Summary: COVID-19 decision model tool
Home-page: https://github.com/restartus/covid-projection
Author: Restart Partners
Author-email: lucas@restart.us
License: UNKNOWN
Platform: UNKNOWN
Classifier: Programming Language :: Python :: 3
Classifier: Operating System :: OS Independent
Classifier: License :: OSI Approved :: MIT License
